{"stats":{"minecraft:picked_up":{"minecraft:wheat_seeds":2,"pig_basemod:fossil":8,"minecraft:coal":54},"minecraft:mined":{"minecraft:grass":1,"pig_basemod:fossil_ore":29,"pig_basemod:infected_block":1},"minecraft:custom":{"minecraft:damage_taken":120,"minecraft:time_since_rest":96411,"minecraft:crouch_one_cm":1058,"minecraft:sprint_one_cm":11739,"minecraft:play_time":96411,"minecraft:walk_one_cm":49314,"minecraft:sneak_time":3206,"minecraft:walk_under_water_one_cm":415,"minecraft:mob_kills":3,"minecraft:jump":187,"minecraft:damage_dealt":468,"minecraft:leave_game":35,"minecraft:walk_on_water_one_cm":156,"minecraft:time_since_death":96411,"minecraft:climb_one_cm":6,"minecraft:total_world_time":128374,"minecraft:talked_to_villager":1,"minecraft:fly_one_cm":332654},"minecraft:used":{"minecraft:trident":7,"pig_basemod:infected_block":5,"minecraft:bedrock":8,"minecraft:white_wool":2,"pig_basemod:infected_log":12,"pig_basemod:danchi_wall":7,"minecraft:diamond_pickaxe":35,"minecraft:sand":6,"pig_basemod:infectedfountain":42,"pig_basemod:danchi_block":88,"minecraft:villager_spawn_egg":5,"minecraft:snow_block":9,"pig_basemod:fossil_ore":29,"pig_basemod:fossil":1,"pig_basemod:infector":24,"pig_basemod:infected_leaves":3,"minecraft:white_concrete":8,"pig_basemod:infection_core":22,"pig_basemod:danchi_slab":25,"minecraft:grass":15,"pig_basemod:danchi_stairs":10,"pig_basemod:infected_grass":17},"minecraft:killed":{"pig_basemod:triplane":2,"minecraft:villager":1}},"DataVersion":3465}